{
  "gameId": "2025-09-07-tb-atl",
  "season": 2025,
  "week": 1,
  "kickoffISO": "2025-09-07T17:00:00.000-04:00",
  "venue": {
    "id": "unknown",
    "name": "Atlanta Falcons Stadium",
    "city": "Unknown",
    "state": "Unknown",
    "surface": "grass",
    "indoor": false
  },
  "teams": {
    "away": {
      "id": "27",
      "name": "Tampa Bay Buccaneers",
      "abbreviation": "TB",
      "location": "Tampa Bay",
      "nickname": "Buccaneers",
      "color": "bd1c36",
      "alternateColor": "3e3a35",
      "logo": "https://a.espncdn.com/i/teamlogos/nfl/500/tb.png",
      "record": {
        "wins": 0,
        "losses": 0,
        "ties": 0,
        "winPercentage": 0
      },
      "oddsRecords": {
        "againstSpread": {
          "wins": 0,
          "losses": 0,
          "ties": 0
        },
        "overUnder": {
          "overs": 0,
          "unders": 0,
          "pushes": 0
        },
        "homeAway": {
          "home": {
            "wins": 0,
            "losses": 0,
            "ties": 0
          },
          "away": {
            "wins": 0,
            "losses": 0,
            "ties": 0
          }
        }
      },
      "statistics": {
        "offense": {
          "pointsPerGame": 0,
          "yardsPerGame": 0,
          "passingYards": 0,
          "rushingYards": 0,
          "thirdDownPercentage": 0,
          "redZonePercentage": 0,
          "turnovers": 0
        },
        "defense": {
          "pointsAllowed": 0,
          "yardsAllowed": 0,
          "passingYardsAllowed": 0,
          "rushingYardsAllowed": 0,
          "sacks": 0,
          "interceptions": 0,
          "forcedFumbles": 0
        }
      },
      "injuries": [],
      "keyPlayers": []
    },
    "home": {
      "id": "1",
      "name": "Atlanta Falcons",
      "abbreviation": "ATL",
      "location": "Atlanta",
      "nickname": "Falcons",
      "color": "a71930",
      "alternateColor": "000000",
      "logo": "https://a.espncdn.com/i/teamlogos/nfl/500/atl.png",
      "record": {
        "wins": 0,
        "losses": 0,
        "ties": 0,
        "winPercentage": 0
      },
      "oddsRecords": {
        "againstSpread": {
          "wins": 0,
          "losses": 0,
          "ties": 0
        },
        "overUnder": {
          "overs": 0,
          "unders": 0,
          "pushes": 0
        },
        "homeAway": {
          "home": {
            "wins": 0,
            "losses": 0,
            "ties": 0
          },
          "away": {
            "wins": 0,
            "losses": 0,
            "ties": 0
          }
        }
      },
      "statistics": {
        "offense": {
          "pointsPerGame": 0,
          "yardsPerGame": 0,
          "passingYards": 0,
          "rushingYards": 0,
          "thirdDownPercentage": 0,
          "redZonePercentage": 0,
          "turnovers": 0
        },
        "defense": {
          "pointsAllowed": 0,
          "yardsAllowed": 0,
          "passingYardsAllowed": 0,
          "rushingYardsAllowed": 0,
          "sacks": 0,
          "interceptions": 0,
          "forcedFumbles": 0
        }
      },
      "injuries": [],
      "keyPlayers": []
    }
  },
  "bettingContext": {
    "openingLine": {
      "spread": 1,
      "total": 41.5,
      "moneyline": {
        "home": 225,
        "away": -124
      }
    },
    "currentLine": {
      "spread": 1.5,
      "total": 42,
      "moneyline": {
        "home": 235,
        "away": -134
      }
    },
    "lineMovement": {
      "spreadMovement": 0.5,
      "totalMovement": 0.5,
      "sharpMoney": "none",
      "publicMoney": "none"
    },
    "bettingTrends": {
      "spread": {
        "home": 50,
        "away": 50
      },
      "total": {
        "over": 50,
        "under": 50
      },
      "moneyline": {
        "home": 50,
        "away": 50
      }
    },
    "keyNumbers": {
      "spread": [
        3,
        7,
        10,
        14
      ],
      "total": [
        37,
        41,
        44,
        47,
        51,
        54
      ]
    }
  },
  "trends": [],
  "keyMatchups": [],
  "weather": {
    "temperature": 72,
    "conditions": "clear",
    "windSpeed": 5,
    "humidity": 50
  },
  "dataSources": {
    "teamData": "ESPN API",
    "bettingData": "Real Data",
    "weatherData": "Real Data"
  }
}