{
  "analystId": "fratguy",
  "week": 1,
  "season": 2025,
  "generatedAt": "2025-09-04T22:57:02.168Z",
  "picks": [
    {
      "gameId": "2025-09-07-cin-cle",
      "gameDate": "2025-09-07T17:00:00.000-04:00",
      "awayTeam": {
        "id": "CIN",
        "name": "Cincinnati Bengals",
        "nickname": "Bengals",
        "score": null
      },
      "homeTeam": {
        "id": "CLE",
        "name": "Cleveland Browns",
        "nickname": "Browns",
        "score": null
      },
      "marketData": {
        "spread": {
          "away": {
            "line": -5.5,
            "odds": -110
          },
          "home": {
            "line": 5.5,
            "odds": -110
          }
        },
        "total": {
          "over": {
            "line": 47.5,
            "odds": -115
          },
          "under": {
            "line": 47.5,
            "odds": -110
          }
        },
        "moneyline": {
          "away": {
            "odds": -250
          },
          "home": {
            "odds": 210
          }
        }
      },
      "selection": {
        "betType": "moneyline",
        "side": "away",
        "line": 0,
        "odds": -250,
        "units": 1,
        "rationale": "Moneyline lean: CIN at -250. Stat margin (PPG vs opp PA): AWAY +12.53",
        "rationaleCues": [
          "Stat margin (PPG vs opp PA): AWAY +12.53",
          "Form delta (win%): +0",
          "Moneyline movement (away): -275→-250 (25 cents)",
          "Public split (moneyline): 3% home / 97% away"
        ]
      },
      "result": {
        "status": "pending",
        "finalLine": 0,
        "finalOdds": -250,
        "payout": 0,
        "netUnits": 0
      },
      "analystId": "fratguy"
    },
    {
      "gameId": "2025-09-07-det-gb",
      "gameDate": "2025-09-07T20:25:00.000-04:00",
      "awayTeam": {
        "id": "DET",
        "name": "Detroit Lions",
        "nickname": "Lions",
        "score": null
      },
      "homeTeam": {
        "id": "GB",
        "name": "Green Bay Packers",
        "nickname": "Packers",
        "score": null
      },
      "marketData": {
        "spread": {
          "away": {
            "line": 1.5,
            "odds": 100
          },
          "home": {
            "line": -1.5,
            "odds": -120
          }
        },
        "total": {
          "over": {
            "line": 47.5,
            "odds": 100
          },
          "under": {
            "line": 47.5,
            "odds": -120
          }
        },
        "moneyline": {
          "away": {
            "odds": 110
          },
          "home": {
            "odds": -130
          }
        }
      },
      "selection": {
        "betType": "total",
        "side": "over",
        "line": 47.5,
        "odds": 100,
        "units": 1,
        "rationale": "Total lean: OVER 47.5 at +100. Expected total 53.15 vs market 47.5",
        "rationaleCues": [
          "Expected total 53.15 vs market 47.5",
          "Total movement: 49.5→47.5 (under)",
          "Public split (total): 14% over / 86% under",
          "Defensive disruption (combined sacks+INTs): 5.25",
          "Passing volume proxy (combined pass yards): 276"
        ]
      },
      "result": {
        "status": "pending",
        "finalLine": 47.5,
        "finalOdds": 100,
        "payout": 0,
        "netUnits": 0
      },
      "analystId": "fratguy"
    },
    {
      "gameId": "2025-09-05-dal-phi",
      "gameDate": "2025-09-05T00:20:00.000-04:00",
      "awayTeam": {
        "id": "DAL",
        "name": "Dallas Cowboys",
        "nickname": "Cowboys",
        "score": null
      },
      "homeTeam": {
        "id": "PHI",
        "name": "Philadelphia Eagles",
        "nickname": "Eagles",
        "score": null
      },
      "marketData": {
        "spread": {
          "away": {
            "line": 8.5,
            "odds": -115
          },
          "home": {
            "line": -8.5,
            "odds": -105
          }
        },
        "total": {
          "over": {
            "line": 47.5,
            "odds": -115
          },
          "under": {
            "line": 47.5,
            "odds": -105
          }
        },
        "moneyline": {
          "away": {
            "odds": 320
          },
          "home": {
            "odds": -425
          }
        }
      },
      "selection": {
        "betType": "moneyline",
        "side": "away",
        "line": 0,
        "odds": 320,
        "units": 1,
        "rationale": "Moneyline lean: DAL at +320. Stat margin (PPG vs opp PA): AWAY +3.06",
        "rationaleCues": [
          "Stat margin (PPG vs opp PA): AWAY +3.06",
          "Form delta (win%): +0",
          "Moneyline movement (away): 230→340 (110 cents)",
          "Public split (moneyline): 91% home / 9% away"
        ]
      },
      "result": {
        "status": "pending",
        "finalLine": 0,
        "finalOdds": 320,
        "payout": 0,
        "netUnits": 0
      },
      "analystId": "fratguy"
    },
    {
      "gameId": "2025-09-08-bal-buf",
      "gameDate": "2025-09-08T00:20:00.000-04:00",
      "awayTeam": {
        "id": "BAL",
        "name": "Baltimore Ravens",
        "nickname": "Ravens",
        "score": null
      },
      "homeTeam": {
        "id": "BUF",
        "name": "Buffalo Bills",
        "nickname": "Bills",
        "score": null
      },
      "marketData": {
        "spread": {
          "away": {
            "line": 1.5,
            "odds": -125
          },
          "home": {
            "line": -1.5,
            "odds": 102
          }
        },
        "total": {
          "over": {
            "line": 50.5,
            "odds": -110
          },
          "under": {
            "line": 50.5,
            "odds": -110
          }
        },
        "moneyline": {
          "away": {
            "odds": -115
          },
          "home": {
            "odds": -105
          }
        }
      },
      "selection": {
        "betType": "total",
        "side": "over",
        "line": 50.5,
        "odds": -110,
        "units": 1,
        "rationale": "Total lean: OVER 50.5 at -110. Expected total 54.89 vs market 50.5",
        "rationaleCues": [
          "Expected total 54.89 vs market 50.5",
          "Total movement: 51.5→50.5 (under)",
          "Public split (total): 13% over / 87% under",
          "Defensive disruption (combined sacks+INTs): 4.67",
          "Passing volume proxy (combined pass yards): 392"
        ]
      },
      "result": {
        "status": "pending",
        "finalLine": 50.5,
        "finalOdds": -110,
        "payout": 0,
        "netUnits": 0
      },
      "analystId": "fratguy"
    },
    {
      "gameId": "2025-09-08-bal-buf",
      "gameDate": "2025-09-08T00:20:00.000-04:00",
      "awayTeam": {
        "id": "BAL",
        "name": "Baltimore Ravens",
        "nickname": "Ravens",
        "score": null
      },
      "homeTeam": {
        "id": "BUF",
        "name": "Buffalo Bills",
        "nickname": "Bills",
        "score": null
      },
      "marketData": {
        "spread": {
          "away": {
            "line": 1.5,
            "odds": -125
          },
          "home": {
            "line": -1.5,
            "odds": 102
          }
        },
        "total": {
          "over": {
            "line": 50.5,
            "odds": -110
          },
          "under": {
            "line": 50.5,
            "odds": -110
          }
        },
        "moneyline": {
          "away": {
            "odds": -115
          },
          "home": {
            "odds": -105
          }
        }
      },
      "selection": {
        "betType": "moneyline",
        "side": "home",
        "line": 0,
        "odds": -105,
        "units": 1,
        "rationale": "Moneyline lean: BUF at -105. Stat margin (PPG vs opp PA): HOME -0.82",
        "rationaleCues": [
          "Stat margin (PPG vs opp PA): HOME -0.82",
          "Form delta (win%): +0",
          "Moneyline movement (home): -120→0 (120 cents)",
          "Public split (moneyline): 21% home / 79% away"
        ]
      },
      "result": {
        "status": "pending",
        "finalLine": 0,
        "finalOdds": -105,
        "payout": 0,
        "netUnits": 0
      },
      "analystId": "fratguy"
    }
  ],
  "weekSummary": {
    "totalPicks": 5,
    "totalUnits": 5,
    "weekPayout": 0,
    "weekNetUnits": 0
  }
}